rich_argparse.py
rich_argparse-stubs/__init__.pyi
rich_argparse-0.7.0.dist-info/METADATA
rich_argparse-0.7.0.dist-info/WHEEL
rich_argparse-0.7.0.dist-info/licenses/LICENSE
rich_argparse-0.7.0.dist-info/RECORD
