Metadata-Version: 2.1
Name: rich_argparse
Version: 0.7.0
Summary: A rich help formatter for argparse
Project-URL: Homepage, https://github.com/hamdanal/rich-argparse
Project-URL: Documentation, https://github.com/hamdanal/rich-argparse#rich-argparse
Project-URL: Issue-Tracker, https://github.com/hamdanal/rich-argparse/issues
Project-URL: Changelog, https://github.com/hamdanal/rich-argparse/blob/main/CHANGELOG.md
Author-email: Ali Hamdan <ali.hamdan.dev@gmail.com>
License-Expression: MIT
License-File: LICENSE
Keywords: argparse,help-formatter,rich
Classifier: Development Status :: 4 - Beta
Classifier: Environment :: Console
Classifier: Intended Audience :: Developers
Classifier: License :: OSI Approved :: MIT License
Classifier: Operating System :: OS Independent
Classifier: Programming Language :: Python :: 3.7
Classifier: Programming Language :: Python :: 3.8
Classifier: Programming Language :: Python :: 3.9
Classifier: Programming Language :: Python :: 3.10
Classifier: Programming Language :: Python :: 3.11
Classifier: Programming Language :: Python :: 3.12
Requires-Python: >=3.7
Requires-Dist: rich>=11.0.0
